CHANGES
CONTRIBUTORS
LICENCE
MANIFEST.in
README
setup.cfg
setup.py
pypi2rpm/__init__.py
pypi2rpm/pypi2rpm.py
pypi2rpm.egg-info/PKG-INFO
pypi2rpm.egg-info/SOURCES.txt
pypi2rpm.egg-info/dependency_links.txt
pypi2rpm.egg-info/requires.txt
pypi2rpm.egg-info/top_level.txt
pypi2rpm/command/__init__.py
pypi2rpm/command/bdist_rpm2.py