Metadata-Version: 1.0
Name: pypi2rpm
Version: 0.6.0
Summary: Script that transforms a sdist archive into a rpm archive
Home-page: http://bitbucket.org/tarek/pypi2rpm
Author: Tarek Ziade
Author-email: tarek@mozilla.com
License: MPL
Platform: UNKNOWN
